sicsoft_dominio/__init__.py
sicsoft_dominio/dominio_auto.py
sicsoft_dominio-0.1.8.dist-info/METADATA
sicsoft_dominio-0.1.8.dist-info/WHEEL
sicsoft_dominio-0.1.8.dist-info/RECORD
