Metadata-Version: 2.1
Name: sicsoft_dominio
Version: 0.1.8
Summary: 
Author: Sicsoft
Requires-Python: >=3.12,<4.0
Classifier: Programming Language :: Python :: 3
Classifier: Programming Language :: Python :: 3.12
Classifier: Programming Language :: Python :: 3.13
Requires-Dist: pywinauto (>=0.6.8,<0.7.0)
